zcached/__init__.py
zcached/backoff.py
zcached/client.py
zcached/connection.py
zcached/deserializer.py
zcached/enums.py
zcached/reader.py
zcached/result.py
zcached/serializer.py
zcached.py-1.2.1.dist-info/LICENSE
zcached.py-1.2.1.dist-info/METADATA
zcached.py-1.2.1.dist-info/WHEEL
zcached.py-1.2.1.dist-info/top_level.txt
zcached.py-1.2.1.dist-info/RECORD
