Metadata-Version: 2.1
Name: zcached.py
Version: 1.2.1
Summary: A lightweight client-side library for zcached, written in Python.
Home-page: https://github.com/xXenvy/zcached.py
Author: xXenvy
Project-URL: Bug Reports, https://github.com/xXenvy/zcached.py/issues
Project-URL: Source, https://github.com/xXenvy/zcached.py
Classifier: Development Status :: 5 - Production/Stable
Classifier: Intended Audience :: Developers
Classifier: License :: OSI Approved :: MIT License
Classifier: Programming Language :: Python :: 3.8
Classifier: Programming Language :: Python :: 3.9
Classifier: Programming Language :: Python :: 3.10
Classifier: Programming Language :: Python :: 3.11
Classifier: Programming Language :: Python :: 3.12
Classifier: Programming Language :: Python :: Implementation :: CPython
Classifier: Typing :: Typed
Classifier: Topic :: Software Development :: Libraries
Classifier: Topic :: Software Development :: Libraries :: Python Modules
Requires-Python: >=3.8
License-File: LICENSE
Requires-Dist: typing-extensions
